ghooks/__init__.py
ghooks/hooks.py
ghooks-0.1.1.dist-info/DESCRIPTION.rst
ghooks-0.1.1.dist-info/METADATA
ghooks-0.1.1.dist-info/RECORD
ghooks-0.1.1.dist-info/WHEEL
ghooks-0.1.1.dist-info/metadata.json
ghooks-0.1.1.dist-info/top_level.txt
