Metadata-Version: 2.0
Name: ghooks
Version: 0.1.1
Summary: GitHub hooks made simpler to handle!
Home-page: https://github.com/meetmangukiya/ghooks
Author: Meet Mangukiya
Author-email: meetmangukiya98@gmail.com
License: MIT
Platform: UNKNOWN
Requires-Dist: flask
